Workbook

Sheet Сравнение
A1: Варианты 1–3 млн ₽: глубина обязательна во всех, различие — класс надёжности
A2: Во всех вариантах — калиброванный риг «перед/зад» на промкамерах с global shutter: это условие измерения глубины (two-view, режим E). Цены — розница РФ, июль 2026, с НДС; «оценка» — уточнить счетами. Синим — редактируемые значения, чёрным — формулы, зелёным — ссылки на листы.
A4: Параметр | B4: В1 «Базовый» | C4: В2 «Надёжный» — РЕКОМЕНДУЕМЫЙ | D4: В3 «Резервированный»
A5: ИТОГО оборудование, ₽ | B5: =В1_Базовый!H25 -> 1202000 | C5: =В2_Надёжный!H25 -> 1988000 | D5: =В3_Резервированный!H31 -> 2719000
A6: ВСЕГО с резервом 10%, ₽ | B6: =В1_Базовый!H27 -> 1322000 | C6: =В2_Надёжный!H27 -> 2187000 | D6: =В3_Резервированный!H33 -> 2991000
A7: Измерение глубины (two-view, режим E) | B7: ДА — риг 8,9 Мп | C7: ДА — риг 12,3 Мп | D7: ДА — риг 12,3 Мп
A8: Бортовой компьютер | B8: Мини-ПК x86 + DC-UPS (потребительский класс — главный компромисс) | C8: Neousys транспортного исполнения: вибро/−25…+60 °C/ignition/суперконденсаторы | D8: Neousys транспортного исполнения
A9: Безотказность борта | B9: Средняя: выдержит пилот, для ежедневной эксплуатации — риск | C9: Высокая: класс подвижного состава | D9: Высокая + горячий ЗИП (камера, объектив, SSD)
A10: Сервер / АРМ | B10: Совмещены в одном ПК (RTX 5070 Ti, RAID1 32 ТБ) | C10: Выделенный сервер (RAID1 40 ТБ) + АРМ-мониторы | D10: Выделенный сервер + ОТДЕЛЬНЫЙ АРМ + онлайн-ИБП 2 кВА
A11: Защита данных | B11: RAID1 на ПК | C11: RAID1 на сервере + WiFi-автовыгрузка | D11: RAID1 + независимый NAS-бэкап (3-2-1) + подменный SSD
A12: Геопривязка | B12: ZED-F9R (RTK+IMU+PPS) | C12: ZED-F9R + survey-антенна | D12: ZED-F9R + СВОЯ базовая станция RTK (см без абонентки)
A13: Выгрузка данных | B13: SSD/SD вручную | C13: WiFi в депо автоматически | D13: WiFi в депо + мост на дальнюю стоянку
A14: Ground truth / юридика | B14: Рейка 3 м С ПОВЕРКОЙ | C14: Рейка 3 м С ПОВЕРКОЙ | D14: Рейка с поверкой + DISTO X3 с поверкой
A15: Остаточные риски | B15: Отказ мини-ПК в вибрации/морозе; простой на время ремонта; ручной перенос данных | C15: Единственный комплект камер: отказ узла = простой до поставки (4–8 недель) | D15: Минимальные в этой рамке; не покрыто: вторая машина (опция), ИНС-тангаж (опция)
A16: Путь апгрейда | B16: → В2: замена мини-ПК на Neousys (550 тыс.), камеры остаются | C16: → В3: +ЗИП, +NAS, +АРМ, +база RTK (~810 тыс.) | D16: → вторая риговая машина (1,28 млн) или профессиональная спецификация (~10,9 млн)
A18: Почему «безотказно» = В2/В3: единственная деталь, которая живёт в вибрации, пыли, морозе и скачках бортсети каждый день — бортовой компьютер. Транспортное исполнение (Neousys) спроектировано именно под это (ignition control, суперконденсаторный ИБП — ни один кадр не теряется при глушении). Камеры Hikrobot промышленные во всех вариантах; сервер в тепле — там достаточно RAID и ИБП. Сантиметры глубины включаются в продуктив после полевого пилота против поверенной рейки (10–15 ям) — это встроенный этап, не доп. расход.

Sheet В1_Базовый
A1: Вариант 1 «Базовый» — 1 риговая машина, ориентир 1,3 млн ₽
A2: Глубина: ЕСТЬ (риг global shutter + two-view). Компромиссы ради бюджета: бортовой мини-ПК потребительского класса, сервер совмещён с АРМ, перенос данных SSD/SD вручную.
A3: № | B3: Наименование | C3: Назначение / обоснование | D3: Модель-пример | E3: Ед. | F3: Кол-во | G3: Цена за ед., ₽ | H3: Сумма, ₽ | I3: Ориентир цены (июль 2026) | J3: Примечание
B4: БЛОК А. Риговая машина — базовое исполнение (глубина)
A5: 1 | B5: Промкамера 8,9 Мп global shutter GigE + кожух с обогревом | C5: Перед + зад. Global shutter обязателен для измерений на ходу (60 км/ч = смаз 17 мм/мс) | D5: Hikrobot MV-CS089-10GC (Sony IMX267) + кожух Wizebox | E5: компл | F5: 2 | G5: 125000 | H5: =F5*G5 -> 250000 | I5: камера 100–140 тыс. + кожух 10–25 тыс. | J5: НЕ брать «20 Мп» на IMX183/226 — rolling shutter
A6: 2 | B6: Объектив C-mount 12 Мп | D6: Hikrobot MVL-KF1228M-12MP | E6: шт | F6: 2 | G6: 30000 | H6: =F6*G6 -> 60000 | I6: оценка 25–45 тыс.
A7: 3 | B7: Бортовой мини-ПК x86 + PoE-инжекторы | C7: Съёмка по дистанции, запись кадров, PPS-синхронизация. Компромисс варианта: потребительское исполнение | D7: мини-ПК (Ryzen 7/Core i5) + 2×PoE+ | E7: компл | F7: 1 | G7: 115000 | H7: =F7*G7 -> 115000 | I7: оценка | J7: Для тиража заменяется транспортным Neousys (см. В2)
A8: 4 | B8: DC-UPS / питание 12 В с задержкой выключения | C8: Корректное завершение записи при глушении двигателя | D8: Mini-Box OpenUPS / аналог | E8: шт | F8: 1 | G8: 25000 | H8: =F8*G8 -> 25000 | I8: оценка 15–30 тыс.
A9: 5 | B9: NVMe SSD 2 ТБ | C9: Буфер смен | D9: Samsung 990 Pro 2TB | E9: шт | F9: 1 | G9: 18000 | H9: =F9*G9 -> 18000 | I9: оценка
A10: 6 | B10: GNSS RTK-модуль с IMU и PPS + антенна | C10: Геопривязка, триггер по дистанции, первичный тангаж | D10: u-blox ZED-F9R + антенна | E10: компл | F10: 1 | G10: 70000 | H10: =F10*G10 -> 70000 | I10: оценка 55–75 тыс.
A11: 7 | B11: Крепёж: платформа, кронштейны, виброразвязка | C11: Жёсткий риг = эталон масштаба | E11: компл | F11: 1 | G11: 30000 | H11: =F11*G11 -> 30000 | I11: оценка
A12: 8 | B12: Кабели M12/GigE, PoE, гермовводы | E12: компл | F12: 1 | G12: 20000 | H12: =F12*G12 -> 20000 | I12: оценка
A13: 9 | B13: Монтаж, юстировка, калибровка рига | C13: Интринзики, высота, тангаж | D13: работы | E13: усл | F13: 1 | G13: 30000 | H13: =F13*G13 -> 30000 | I13: оценка
B14: БЛОК Б. Сервер и АРМ (совмещённые)
A15: 10 | B15: ПК «сервер + АРМ» в одном | C15: Скрининг, полный конвейер, two-view фотограмметрия, БД, веб-интерфейс, разметка. Зеркало HDD защищает архив | D15: Ryzen 9 9950X / 64 ГБ DDR5 / RTX 5070 Ti 16 ГБ / NVMe 2 ТБ / 2×16 ТБ HDD (RAID1) | E15: шт | F15: 1 | G15: 400000 | H15: =F15*G15 -> 400000 | I15: RTX 5070 Ti — от 97 990 (regard.ru); остальное оценка
A16: 11 | B16: Монитор 27" 4K IPS | C16: Разметка и контроль | D16: LG 27UP650 | E16: шт | F16: 1 | G16: 45000 | H16: =F16*G16 -> 45000 | I16: оценка
A17: 12 | B17: ИБП 1500 ВА | D17: Ippon Back Basic 1500 | E17: шт | F17: 1 | G17: 17000 | H17: =F17*G17 -> 17000 | I17: nix.ru — 16 690
A18: 13 | B18: Периферия | D18: клавиатура + мышь | E18: компл | F18: 1 | G18: 8000 | H18: =F18*G18 -> 8000 | I18: оценка
B19: БЛОК Г. Калибровка и контрольные замеры (ground truth)
A20: 14 | B20: Калибровочные мишени | C20: Шахматка (интринзики) + ChArUco (режим ручной досъёмки) | D20: УФ-печать на ПВХ 5 мм / алюкобонде | E20: компл | F20: 1 | G20: 10000 | H20: =F20*G20 -> 10000 | I20: оценка (лист ПВХ — от 1 390, poliservis.com)
A21: 15 | B21: Рейка дорожная 3 м с промерным клином, С ПОВЕРКОЙ | C21: Ground truth глубины: валидация two-view на пилоте (10–15 ям) и юридически значимые акты по ГОСТ Р 50597 | D21: РДУ «Кондор» (ГОСТ 30412) | E21: шт | F21: 1 | G21: 58000 | H21: =F21*G21 -> 58000 | I21: rusgeocom.ru — 58 000 | J21: Продление поверки ~8 тыс./год
A22: 16 | B22: Лазерный дальномер + мерный инструмент | C22: Дистанции съёмки, высота рига при калибровке | D22: Bosch GLM 50 + рулетка/линейка | E22: компл | F22: 1 | G22: 18000 | H22: =F22*G22 -> 18000 | I22: оценка
A23: 17 | B23: Комплект безопасности на машину | C23: Работы на проезжей части при контрольных замерах | D23: 2 жилета + 4 конуса с утяжелителем + знак | E23: компл | F23: 1 | G23: 8000 | H23: =F23*G23 -> 8000 | I23: оценка
A24: 18 | B24: Внешний SSD 2 ТБ USB-C | C24: Резервный канал переноса данных | D24: Samsung T7 | E24: шт | F24: 1 | G24: 20000 | H24: =F24*G24 -> 20000 | I24: оценка 18–22 тыс.
B25: ИТОГО | H25: =H5+H6+H7+H8+H9+H10+H11+H12+H13+H15+H16+H17+H18+H20+H21+H22+H23+H24 -> 1202000
B26: Резерв на непредвиденные, 10% | H26: =ROUND(H25*0.1,-3) -> 120000
B27: ВСЕГО с резервом | H27: =H25+H26 -> 1322000

Sheet В2_Надёжный
A1: Вариант 2 «Надёжный» (РЕКОМЕНДУЕМЫЙ) — 1 риговая машина транспортного исполнения, ориентир 2,2 млн ₽
A2: Глубина: ЕСТЬ. Безотказность борта: транспортный ПК Neousys (вибро/температура/ignition/суперконденсаторный ИБП), камеры 12,3 Мп в кожухах с обогревом, автовыгрузка по WiFi, выделенный сервер с зеркалом.
A3: № | B3: Наименование | C3: Назначение / обоснование | D3: Модель-пример | E3: Ед. | F3: Кол-во | G3: Цена за ед., ₽ | H3: Сумма, ₽ | I3: Ориентир цены (июль 2026) | J3: Примечание
B4: БЛОК А. Риговая машина — транспортное исполнение (глубина, безотказно)
A5: 1 | B5: Промкамера 12,3 Мп global shutter GigE, IP-кожух с обогревом | C5: Перед + зад. Global shutter обязателен для измерений на ходу (60 км/ч = смаз 17 мм/мс); 12,3 Мп ≈ 1–1,5 мм/px в рабочей зоне 2,5–5 м | D5: Hikrobot MV-CS120-10GC (Sony IMX253) + кожух Wizebox | E5: компл | F5: 2 | G5: 182000 | H5: =F5*G5 -> 364000 | I5: камера 130–180 тыс. (mallenom.ru, digitoria.ru) + кожух 10–25 тыс. (wizebox.ru) | J5: НЕ брать «20 Мп» на IMX183/226 — rolling shutter
A6: 2 | B6: Объектив C-mount 12 Мп, 1.1" | C6: Полоса дороги целиком с 2,5–8 м | D6: Hikrobot MVL-KF1228M-12MP | E6: шт | F6: 2 | G6: 40000 | H6: =F6*G6 -> 80000 | I6: оценка 25–45 тыс.
A7: 3 | B7: Бортовой ПК транспортного исполнения | C7: КЛЮЧ К БЕЗОТКАЗНОСТИ БОРТА: вибростойкость, −25…+60 °C, питание 8–48 В, ignition control, PoE+ камерам, встроенный ИБП на суперконденсаторах — корректное завершение записи при любом глушении | D7: Neousys Nuvo-7250VTC | E7: шт | F7: 1 | G7: 550000 | H7: =F7*G7 -> 550000 | I7: оценка 450–700 тыс. (nnz-ipc.ru, ipc2u.ru — по запросу) | J7: Срок поставки 6–12 недель — заказывать первым
A8: 4 | B8: NVMe SSD 4 ТБ | C8: Буфер смен с недельным запасом | D8: Samsung 990 Pro 4TB | E8: шт | F8: 1 | G8: 70000 | H8: =F8*G8 -> 70000 | I8: regard.ru — 69 990
A9: 5 | B9: GNSS RTK-модуль с IMU и PPS + survey-антенна | C9: Геопривязка кадров, триггер съёмки по дистанции, первичный тангаж; RTK 1–2 см при поправках | D9: u-blox ZED-F9R + антенна Harxon | E9: компл | F9: 1 | G9: 80000 | H9: =F9*G9 -> 80000 | I9: оценка 55–90 тыс.
A10: 6 | B10: Крепёж: платформа, кронштейны, виброразвязка | C10: Жёсткий риг = постоянный эталон масштаба (калибровка высоты/тангажа) | E10: компл | F10: 1 | G10: 50000 | H10: =F10*G10 -> 50000 | I10: оценка 30–70 тыс.
A11: 7 | B11: Кабели M12/GigE, PoE, гермовводы, проводка | E11: компл | F11: 1 | G11: 30000 | H11: =F11*G11 -> 30000 | I11: оценка
A12: 8 | B12: Монтаж на автомобиль, юстировка, калибровка рига | C12: Интринзики (шахматка), высота, тангаж; протокол калибровки | D12: работы | E12: усл | F12: 1 | G12: 60000 | H12: =F12*G12 -> 60000 | I12: оценка | J12: Повторять после каждого демонтажа
B13: БЛОК Б. Сервер и АРМ
A14: 9 | B14: Сервер-ПК (выделенный) | C14: Конвейер, фотограмметрия, БД PostGIS, веб; дообучение YOLO ночами. Зеркало 2×20 ТБ | D14: Ryzen 9 9950X / 96 ГБ DDR5 / RTX 5070 Ti 16 ГБ / NVMe 4 ТБ / 2×20 ТБ (RAID1) | E14: шт | F14: 1 | G14: 450000 | H14: =F14*G14 -> 450000 | I14: RTX 5070 Ti от 97 990 (regard.ru); HDD/RAM — оценка при дефиците 2026
A15: 10 | B15: Монитор 27" 4K IPS | C15: АРМ: разметка + реестр/карта | D15: LG 27UP650 | E15: шт | F15: 2 | G15: 45000 | H15: =F15*G15 -> 90000 | I15: оценка
A16: 11 | B16: ИБП 1500 ВА | D16: Ippon Back Basic 1500 | E16: шт | F16: 1 | G16: 17000 | H16: =F16*G16 -> 17000 | I16: nix.ru — 16 690
A17: 12 | B17: Периферия | D17: Logitech + гарнитура | E17: компл | F17: 1 | G17: 15000 | H17: =F17*G17 -> 15000 | I17: оценка
A18: 13 | B18: Точка доступа WiFi 6 в депо | C18: Автовыгрузка смены (10–15 ГБ кадров) при заезде — без ручных операций | D18: TP-Link Omada EAP670 + PoE | E18: шт | F18: 1 | G18: 18000 | H18: =F18*G18 -> 18000 | I18: tplink.com.ru — 17 090
B19: БЛОК Г. Калибровка и контрольные замеры (ground truth)
A20: 14 | B20: Калибровочные мишени | C20: Шахматка (интринзики) + ChArUco (режим ручной досъёмки) | D20: УФ-печать на ПВХ 5 мм / алюкобонде | E20: компл | F20: 1 | G20: 10000 | H20: =F20*G20 -> 10000 | I20: оценка (лист ПВХ — от 1 390, poliservis.com)
A21: 15 | B21: Рейка дорожная 3 м с промерным клином, С ПОВЕРКОЙ | C21: Ground truth глубины: валидация two-view на пилоте (10–15 ям) и юридически значимые акты по ГОСТ Р 50597 | D21: РДУ «Кондор» (ГОСТ 30412) | E21: шт | F21: 1 | G21: 58000 | H21: =F21*G21 -> 58000 | I21: rusgeocom.ru — 58 000 | J21: Продление поверки ~8 тыс./год
A22: 16 | B22: Лазерный дальномер + мерный инструмент | C22: Дистанции съёмки, высота рига при калибровке | D22: Bosch GLM 50 + рулетка/линейка | E22: компл | F22: 1 | G22: 18000 | H22: =F22*G22 -> 18000 | I22: оценка
A23: 17 | B23: Комплект безопасности на машину | C23: Работы на проезжей части при контрольных замерах | D23: 2 жилета + 4 конуса с утяжелителем + знак | E23: компл | F23: 1 | G23: 8000 | H23: =F23*G23 -> 8000 | I23: оценка
A24: 18 | B24: Внешний SSD 2 ТБ USB-C | C24: Резервный канал переноса данных | D24: Samsung T7 | E24: шт | F24: 1 | G24: 20000 | H24: =F24*G24 -> 20000 | I24: оценка 18–22 тыс.
B25: ИТОГО | H25: =H5+H6+H7+H8+H9+H10+H11+H12+H14+H15+H16+H17+H18+H20+H21+H22+H23+H24 -> 1988000
B26: Резерв на непредвиденные, 10% | H26: =ROUND(H25*0.1,-3) -> 199000
B27: ВСЕГО с резервом | H27: =H25+H26 -> 2187000

Sheet В3_Резервированный
A1: Вариант 3 «Резервированный» — В2 + горячий ЗИП и отказоустойчивый тыл, ориентир 3,0 млн ₽
A2: Глубина: ЕСТЬ. Максимальная безотказность в рамке 3 млн: запасная камера и SSD на борт, независимый NAS-бэкап, онлайн-ИБП, отдельный АРМ (сервер не останавливается), своя RTK-база, поверенный дальномер.
A3: № | B3: Наименование | C3: Назначение / обоснование | D3: Модель-пример | E3: Ед. | F3: Кол-во | G3: Цена за ед., ₽ | H3: Сумма, ₽ | I3: Ориентир цены (июль 2026) | J3: Примечание
B4: БЛОК А. Риговая машина — транспортное исполнение (глубина, безотказно)
A5: 1 | B5: Промкамера 12,3 Мп global shutter GigE, IP-кожух с обогревом | C5: Перед + зад. Global shutter обязателен для измерений на ходу (60 км/ч = смаз 17 мм/мс); 12,3 Мп ≈ 1–1,5 мм/px в рабочей зоне 2,5–5 м | D5: Hikrobot MV-CS120-10GC (Sony IMX253) + кожух Wizebox | E5: компл | F5: 2 | G5: 182000 | H5: =F5*G5 -> 364000 | I5: камера 130–180 тыс. (mallenom.ru, digitoria.ru) + кожух 10–25 тыс. (wizebox.ru) | J5: НЕ брать «20 Мп» на IMX183/226 — rolling shutter
A6: 2 | B6: Объектив C-mount 12 Мп, 1.1" | C6: Полоса дороги целиком с 2,5–8 м | D6: Hikrobot MVL-KF1228M-12MP | E6: шт | F6: 2 | G6: 40000 | H6: =F6*G6 -> 80000 | I6: оценка 25–45 тыс.
A7: 3 | B7: Бортовой ПК транспортного исполнения | C7: КЛЮЧ К БЕЗОТКАЗНОСТИ БОРТА: вибростойкость, −25…+60 °C, питание 8–48 В, ignition control, PoE+ камерам, встроенный ИБП на суперконденсаторах — корректное завершение записи при любом глушении | D7: Neousys Nuvo-7250VTC | E7: шт | F7: 1 | G7: 550000 | H7: =F7*G7 -> 550000 | I7: оценка 450–700 тыс. (nnz-ipc.ru, ipc2u.ru — по запросу) | J7: Срок поставки 6–12 недель — заказывать первым
A8: 4 | B8: NVMe SSD 4 ТБ | C8: Буфер смен с недельным запасом | D8: Samsung 990 Pro 4TB | E8: шт | F8: 1 | G8: 70000 | H8: =F8*G8 -> 70000 | I8: regard.ru — 69 990
A9: 5 | B9: GNSS RTK-модуль с IMU и PPS + survey-антенна | C9: Геопривязка кадров, триггер съёмки по дистанции, первичный тангаж; RTK 1–2 см при поправках | D9: u-blox ZED-F9R + антенна Harxon | E9: компл | F9: 1 | G9: 80000 | H9: =F9*G9 -> 80000 | I9: оценка 55–90 тыс.
A10: 6 | B10: Крепёж: платформа, кронштейны, виброразвязка | C10: Жёсткий риг = постоянный эталон масштаба (калибровка высоты/тангажа) | E10: компл | F10: 1 | G10: 50000 | H10: =F10*G10 -> 50000 | I10: оценка 30–70 тыс.
A11: 7 | B11: Кабели M12/GigE, PoE, гермовводы, проводка | E11: компл | F11: 1 | G11: 30000 | H11: =F11*G11 -> 30000 | I11: оценка
A12: 8 | B12: Монтаж на автомобиль, юстировка, калибровка рига | C12: Интринзики (шахматка), высота, тангаж; протокол калибровки | D12: работы | E12: усл | F12: 1 | G12: 60000 | H12: =F12*G12 -> 60000 | I12: оценка | J12: Повторять после каждого демонтажа
B13: БЛОК Б. Горячий ЗИП борта (безотказность: замена узла за час)
A14: 9 | B14: Запасная камера + объектив | C14: Продолжение работ при отказе/повреждении любого канала | D14: Hikrobot MV-CS120-10GC + MVL-KF1228M | E14: компл | F14: 1 | G14: 200000 | H14: =F14*G14 -> 200000 | I14: по ценам блока А
A15: 10 | B15: Запасной бортовой SSD 4 ТБ | C15: Подменный носитель — смена не теряется | D15: Samsung 990 Pro 4TB | E15: шт | F15: 1 | G15: 70000 | H15: =F15*G15 -> 70000 | I15: regard.ru — 69 990
B16: БЛОК В. Сервер, АРМ, сеть, резервирование
A17: 11 | B17: Сервер-ПК (выделенный) | C17: Конвейер, фотограмметрия, БД, веб, дообучение | D17: Ryzen 9 9950X / 96 ГБ / RTX 5070 Ti / NVMe 4 ТБ / 2×20 ТБ (RAID1) | E17: шт | F17: 1 | G17: 450000 | H17: =F17*G17 -> 450000 | I17: RTX 5070 Ti от 97 990 (regard.ru)
A18: 12 | B18: ИБП online 2 кВА | C18: Двойное преобразование — сервер переживает любые скачки сети | D18: Ippon Innova RT 2000 / Powercom | E18: шт | F18: 1 | G18: 60000 | H18: =F18*G18 -> 60000 | I18: оценка 45–80 тыс.
A19: 13 | B19: NAS 4 отсека + 2×16 ТБ | C19: НЕЗАВИСИМЫЙ бэкап БД и архива кадров (правило 3-2-1) | D19: QNAP/Synology 4-bay + IronWolf Pro | E19: компл | F19: 1 | G19: 170000 | H19: =F19*G19 -> 170000 | I19: оценка
A20: 14 | B20: АРМ оператора (отдельный от сервера) | C20: Разметка/контроль не мешают конвейеру; сервер работает без перерывов | D20: Ryzen 5 / 32 ГБ / NVMe 1 ТБ + 2× монитора 27" 4K | E20: компл | F20: 1 | G20: 240000 | H20: =F20*G20 -> 240000 | I20: оценка (ПК ~150 тыс. + 2×45 тыс. мониторы)
A21: 15 | B21: ИБП 1500 ВА для АРМ | D21: Ippon Back Basic 1500 | E21: шт | F21: 1 | G21: 17000 | H21: =F21*G21 -> 17000 | I21: nix.ru — 16 690
A22: 16 | B22: Периферия | D22: Logitech + гарнитура | E22: компл | F22: 1 | G22: 15000 | H22: =F22*G22 -> 15000 | I22: оценка
A23: 17 | B23: Точка доступа WiFi 6 + мост на стоянку | C23: Автовыгрузка, даже если машина ночует на дальней стоянке | D23: TP-Link EAP670 + 2×CPE710 | E23: компл | F23: 1 | G23: 38000 | H23: =F23*G23 -> 38000 | I23: tplink.com.ru — 17 090 + мост ~20 тыс.
A24: 18 | B24: Собственная базовая станция RTK | C24: Сантиметровая привязка без абонентской платы | D24: ZED-F9P + антенна на крыше | E24: компл | F24: 1 | G24: 30000 | H24: =F24*G24 -> 30000 | I24: оценка | J24: Альтернатива: EFT-CORS 50 400 ₽/год
B25: БЛОК Г. Калибровка и контрольные замеры (ground truth)
A26: 19 | B26: Калибровочные мишени | C26: Шахматка (интринзики) + ChArUco (режим ручной досъёмки) | D26: УФ-печать на ПВХ 5 мм / алюкобонде | E26: компл | F26: 1 | G26: 10000 | H26: =F26*G26 -> 10000 | I26: оценка (лист ПВХ — от 1 390, poliservis.com)
A27: 20 | B27: Рейка дорожная 3 м с промерным клином, С ПОВЕРКОЙ | C27: Ground truth глубины: валидация two-view на пилоте (10–15 ям) и юридически значимые акты по ГОСТ Р 50597 | D27: РДУ «Кондор» (ГОСТ 30412) | E27: шт | F27: 1 | G27: 58000 | H27: =F27*G27 -> 58000 | I27: rusgeocom.ru — 58 000 | J27: Продление поверки ~8 тыс./год
A28: 21 | B28: Лазерный дальномер IP65 с поверкой | C28: Дистанции съёмки, высота рига при калибровке | D28: Leica DISTO X3 + поверка | E28: компл | F28: 1 | G28: 49000 | H28: =F28*G28 -> 49000 | I28: geooptic.ru — 47 300 + поверка 1 000
A29: 22 | B29: Комплект безопасности на машину | C29: Работы на проезжей части при контрольных замерах | D29: 2 жилета + 4 конуса с утяжелителем + знак | E29: компл | F29: 1 | G29: 8000 | H29: =F29*G29 -> 8000 | I29: оценка
A30: 23 | B30: Внешний SSD 2 ТБ USB-C | C30: Резервный канал переноса данных | D30: Samsung T7 | E30: шт | F30: 1 | G30: 20000 | H30: =F30*G30 -> 20000 | I30: оценка 18–22 тыс.
B31: ИТОГО | H31: =H5+H6+H7+H8+H9+H10+H11+H12+H14+H15+H17+H18+H19+H20+H21+H22+H23+H24+H26+H27+H28+H29+H30 -> 2719000
B32: Резерв на непредвиденные, 10% | H32: =ROUND(H31*0.1,-3) -> 272000
B33: ВСЕГО с резервом | H33: =H31+H32 -> 2991000

Sheet OPEX_Опции
A1: OPEX и опции расширения
A2: Строка «ИТОГО» листа — справочная сумма всех строк, в бюджеты вариантов не входит.
A3: № | B3: Наименование | C3: Назначение / обоснование | D3: Модель-пример | E3: Ед. | F3: Кол-во | G3: Цена за ед., ₽ | H3: Сумма, ₽ | I3: Ориентир цены (июль 2026) | J3: Примечание
B4: OPEX (в год)
A5: 1 | B5: RTK-поправки NTRIP (если без своей базы) | C5: Сантиметровая привязка; для работы движка не обязательна | D5: EFT-CORS (Ростов-на-Дону) | E5: приёмник | F5: 1 | G5: 50400 | H5: =F5*G5 -> 50400 | I5: eft-cors.ru — 50 400 ₽/год | J5: SmartNet — 41 900 ₽/год; в В3 есть своя база → 0
A6: 2 | B6: Продление поверки (рейка, дальномер) | E6: год | F6: 1 | G6: 10000 | H6: =F6*G6 -> 10000 | I6: оценка
A7: 3 | B7: Связь LTE (опция выгрузки с маршрута) | D7: SIM M2M | E7: шт/год | F7: 1 | G7: 8400 | H7: =F7*G7 -> 8400 | I7: оценка 700 ₽/мес
B8: Опции расширения (в итоги вариантов не входят)
A9: 4 | B9: ВТОРАЯ риговая машина, транспортное исполнение | C9: Глубина на втором маршруте | D9: состав блока А варианта В2 | E9: компл | F9: 1 | G9: 1284000 | H9: =F9*G9 -> 1284000 | I9: по ценам В2
A10: 5 | B10: Вторая риговая машина, базовое исполнение | C10: Глубина на втором маршруте, бюджетно | D10: состав блока А варианта В1 | E10: компл | F10: 1 | G10: 618000 | H10: =F10*G10 -> 618000 | I10: по ценам В1
A11: 6 | B11: Машина покрытия на видеорегистраторе | C11: Детекция и реестр без глубины (категорийно) | D11: BlackVue DR970X-2CH + SD + проводка + ZED-F9P | E11: компл | F11: 1 | G11: 131000 | H11: =F11*G11 -> 131000 | I11: alarm.ru — 85 490 + обвязка
A12: 7 | B12: Апгрейд GPU сервера до RTX 5090 32 ГБ | C12: Ускорение дообучения и фотограмметрии | D12: RTX 5090 | E12: шт | F12: 1 | G12: 425000 | H12: =F12*G12 -> 425000 | I12: regard.ru — от 424 990 | J12: Доплата к 5070 Ti ~330 тыс.
A13: 8 | B13: Камеры 24,5 Мп global shutter вместо 12,3 | C13: Запас детализации текстуры дна | D13: Hikrobot MV-CS230-10GC (IMX530) | E13: шт | F13: 2 | G13: 250000 | H13: =F13*G13 -> 500000 | I13: оценка 200–300 тыс.
A14: 9 | B14: Транспортный борт-ПК для В1 (апгрейд мини-ПК) | C14: Довести В1 до надёжности В2 | D14: Neousys Nuvo-7250VTC | E14: шт | F14: 1 | G14: 550000 | H14: =F14*G14 -> 550000 | I14: оценка 450–700 тыс.
A15: 10 | B15: ИНС навигационного класса | C15: Метрологический тангаж ±0,03° (если программного уточнения мало) | D15: ЛМП ГКВ-6 (РФ) | E15: шт | F15: 1 | G15: 500000 | H15: =F15*G15 -> 500000 | I15: оценка 300–800 тыс., mp-lab.ru | J15: По итогам пилота
B16: ИТОГО | H16: =H5+H6+H7+H9+H10+H11+H12+H13+H14+H15 -> 4076800
B17: Резерв на непредвиденные, 10% | H17: =ROUND(H16*0.1,-3) -> 408000
B18: ВСЕГО с резервом | H18: =H16+H17 -> 4484800
