Workbook

Sheet Сравнение
A1: Варианты комплектации 0,5–2 млн ₽ — система учёта дорожных дефектов
A2: Цены — розница РФ, июль 2026, с НДС, ориентировочные (позиции с пометкой «оценка» — уточнить счетами). Синим — редактируемые значения, чёрным — формулы, зелёным — ссылки на листы. Каждый вариант — самостоятельный работоспособный контур; В1→В2→В3 — это лестница апгрейда, железо не выбрасывается.
A4: Параметр | B4: В1 «Старт» | C4: В2 «Пилот+» | D4: В3 «Риг»
A5: ИТОГО оборудование, ₽ | B5: =В1_Старт!H16 -> 475000 | C5: =В2_Пилот!H18 -> 919000 | D5: =В3_Риг!H31 -> 1602000
A6: ВСЕГО с резервом 10%, ₽ | B6: =В1_Старт!H18 -> 523000 | C6: =В2_Пилот!H20 -> 1011000 | D6: =В3_Риг!H33 -> 1762000
A7: Машин в работе | B7: 1 | C7: 2 | D7: 3 (1 риг + 2 регистратора)
A8: Съёмка | B8: VIOFO A229 Pro 2CH (4K+2K) | C8: 2× BlackVue DR970X-2CH (4K+FHD) | D8: 2× промкамеры 8,9 Мп global shutter (риг) + 2× BlackVue
A9: Геопривязка | B9: GPS регистратора + PPS-логгер (2–10 м) | C9: ZED-F9P, RTK-ready (см при поправках) | D9: ZED-F9R RTK+IMU на риге + F9P на остальных
A10: Сервер | B10: Общий ПК с АРМ (RTX 5060 Ti 16 ГБ) | C10: Выделенный ПК (RTX 5070 Ti), 32 ТБ зеркало | D10: Выделенный ПК (RTX 5070 Ti), 40 ТБ зеркало
A11: Выгрузка данных | B11: SD-карта вручную | C11: WiFi в депо (автоматически) | D11: WiFi в депо (автоматически)
A12: Что закрывает | B12: Детекция, реестр с картой и уведомлениями, датасет, категорийная глубина | C12: То же + гео-дедуп повторных проездов, 2 маршрута, поверенный ground truth (акты) | D12: То же + ПИЛОТ ИЗМЕРЕНИЯ ГЛУБИНЫ (two-view, режим E) на калиброванном риге — главный исследовательский вопрос проекта
A13: Чего НЕ закрывает | B13: Сантиметры глубины (rolling shutter), RTK, автовыгрузку | C13: Сантиметры глубины — регистраторы физически не дают метрологию | D13: Транспортное исполнение борта (мини-ПК — компромисс); тираж рига на весь парк
A14: Путь апгрейда | B14: → В2 (добавить машину, сервер, WiFi) | C14: → В3 (добавить риг) | D14: → профессиональная спецификация (отд. файл, ~10,9 млн): транспортные борт-ПК, камеры 12–24 Мп, GPU-сервер, СХД
A16: Честная оговорка (принцип проекта): в В1 и В2 глубина ям выдаётся только категорией «мелкая/средняя/глубокая» — видеорегистраторы физически не обеспечивают измерение в сантиметрах. Сантиметры глубины появляются в В3 на риговой машине — после полевого пилота против рейки.

Sheet В1_Старт
A1: Вариант 1 «Старт» — 1 машина, ориентир 0,5 млн ₽
A2: Минимальный работоспособный контур: детекция дефектов, реестр с картой и уведомлениями, наработка собственного датасета. Перенос данных — на SD-карте вручную. Глубина ям — только категорийно.
A3: № | B3: Наименование | C3: Назначение / обоснование | D3: Модель-пример | E3: Ед. | F3: Кол-во | G3: Цена за ед., ₽ | H3: Сумма, ₽ | I3: Ориентир цены (июль 2026) | J3: Примечание
A4: 1 | B4: Видеорегистратор 2-канальный 4K+2K с GPS | C4: Съёмка перед/зад для детекции дефектов и наработки датасета | D4: VIOFO A229 Pro 2CH | E4: шт | F4: 1 | G4: 35000 | H4: =F4*G4 -> 35000 | I4: оценка 30–40 тыс. (viofo.ru; A139 Pro был 28 990) | J4: Rolling shutter и H.265 — метрологию глубины не даёт (только категория)
A5: 2 | B5: Карта microSD 512 ГБ high-endurance | C5: Носитель записи; смена ≈ 30–60 ГБ видео | D5: Samsung PRO Endurance 512GB | E5: шт | F5: 1 | G5: 9000 | H5: =F5*G5 -> 9000 | I5: оценка
A6: 3 | B6: Скрытая проводка + установка | C6: Питание от бортсети с защитой АКБ | D6: hardwire kit + работы | E6: компл | F6: 1 | G6: 10000 | H6: =F6*G6 -> 10000 | I6: оценка
A7: 4 | B7: GPS-логгер с PPS | C7: Резервный трек и точное время | D7: u-blox NEO-M10 с антенной | E7: шт | F7: 1 | G7: 2000 | H7: =F7*G7 -> 2000 | I7: amperkot.ru — 1 425
A8: 5 | B8: ПК «сервер + АРМ» в одном | C8: Ночной прогон смены (скрининг GPU + полный конвейер), БД, веб-интерфейс, разметка датасета | D8: Ryzen 7 9700X / 64 ГБ DDR5 / RTX 5060 Ti 16 ГБ / NVMe 2 ТБ / HDD 16 ТБ | E8: шт | F8: 1 | G8: 280000 | H8: =F8*G8 -> 280000 | I8: оценка (сборка); движок проекта работает и на CPU | J8: Апгрейд до RTX 5070 Ti (от 97 990, regard.ru) = +40–50 тыс.
A9: 6 | B9: Монитор 27" 4K IPS | C9: Разметка мелких дефектов | D9: LG 27UP650 / Philips 27E1N5900E | E9: шт | F9: 1 | G9: 45000 | H9: =F9*G9 -> 45000 | I9: оценка 35–45 тыс.
A10: 7 | B10: ИБП 1500 ВА | C10: Защита ПК и БД | D10: Ippon Back Basic 1500 Euro | E10: шт | F10: 1 | G10: 17000 | H10: =F10*G10 -> 17000 | I10: nix.ru — 16 690
A11: 8 | B11: Периферия | C11: Клавиатура, мышь | D11: Logitech MK-серия | E11: компл | F11: 1 | G11: 8000 | H11: =F11*G11 -> 8000 | I11: оценка
A12: 9 | B12: Калибровочные мишени | C12: Шахматка + ChArUco (ручной режим досъёмки, интринзики) | D12: УФ-печать на ПВХ 5 мм, А2 | E12: компл | F12: 1 | G12: 6000 | H12: =F12*G12 -> 6000 | I12: оценка (лист ПВХ 3 мм — 1 390, poliservis.com)
A13: 10 | B13: Рейка дорожная 3 м с промерным клином (без поверки) | C13: Ground truth глубины для валидации; поверка добавляется позже при выходе на акты | D13: РДУ-аналог (ГОСТ 30412) | E13: шт | F13: 1 | G13: 40000 | H13: =F13*G13 -> 40000 | I13: nevageo.ru — от 39 600 | J13: С поверкой — 58 000 (rusgeocom.ru)
A14: 11 | B14: Дальномер + рулетка + линейка | C14: Контрольные замеры, высота установки камер | D14: Bosch GLM 50 + STAYER 5 м + линейка ГОСТ 427 | E14: компл | F14: 1 | G14: 15000 | H14: =F14*G14 -> 15000 | I14: оценка
A15: 12 | B15: Комплект безопасности | C15: Работы на проезжей части | D15: 2 жилета + 4 конуса + знак | E15: компл | F15: 1 | G15: 8000 | H15: =F15*G15 -> 8000 | I15: оценка
B16: ИТОГО | H16: =H4+H5+H6+H7+H8+H9+H10+H11+H12+H13+H14+H15 -> 475000
B17: Резерв на непредвиденные, 10% | H17: =ROUND(H16*0.1,-3) -> 48000
B18: ВСЕГО с резервом | H18: =H16+H17 -> 523000

Sheet В2_Пилот
A1: Вариант 2 «Пилот+» — 2 машины, ориентир 1 млн ₽
A2: Тот же контур, что В1, плюс: две машины, выделенный сервер, нормальная геопривязка (ZED-F9P, RTK-ready), автоматическая WiFi-выгрузка в депо, поверенная рейка для юридически значимого ground truth.
A3: № | B3: Наименование | C3: Назначение / обоснование | D3: Модель-пример | E3: Ед. | F3: Кол-во | G3: Цена за ед., ₽ | H3: Сумма, ₽ | I3: Ориентир цены (июль 2026) | J3: Примечание
A4: 1 | B4: Видеорегистратор премиум 2-кан. 4K+FHD с GPS и WiFi | C4: Съёмка перед/зад; WiFi — автоматическая выгрузка в депо | D4: BlackVue DR970X-2CH | E4: шт | F4: 2 | G4: 86000 | H4: =F4*G4 -> 172000 | I4: alarm.ru — 85 490 (в наличии) | J4: Rolling shutter/H.265 — метрологию глубины не даёт
A5: 2 | B5: Карта microSD 256 ГБ high-endurance | D5: Samsung PRO Endurance | E5: шт | F5: 2 | G5: 5000 | H5: =F5*G5 -> 10000 | I5: оценка
A6: 3 | B6: Скрытая проводка + установка | D6: hardwire kit + работы | E6: компл | F6: 2 | G6: 10000 | H6: =F6*G6 -> 20000 | I6: оценка
A7: 4 | B7: GNSS-приёмник RTK-ready с PPS | C7: Точная геопривязка кадров (дедуп повторных проездов); RTK 1–2 см при поправках | D7: u-blox ZED-F9P (плата + антенна) | E7: компл | F7: 2 | G7: 30000 | H7: =F7*G7 -> 60000 | I7: asiaoptom.com — 20–35 тыс. | J7: Параллельный импорт
A8: 5 | B8: Сервер-ПК (выделенный) | C8: Скрининг и конвейер по 2 машинам, БД PostGIS, веб-интерфейс, дообучение YOLO ночами | D8: Ryzen 9 9950X / 64 ГБ DDR5 / RTX 5070 Ti 16 ГБ / NVMe 2 ТБ / 2×16 ТБ HDD (зеркало) | E8: шт | F8: 1 | G8: 400000 | H8: =F8*G8 -> 400000 | I8: RTX 5070 Ti — от 97 990 (regard.ru); остальное оценка
A9: 6 | B9: Монитор 27" 4K IPS | C9: АРМ оператора: разметка + реестр/карта | D9: LG 27UP650 | E9: шт | F9: 2 | G9: 45000 | H9: =F9*G9 -> 90000 | I9: оценка
A10: 7 | B10: ИБП 1500 ВА | D10: Ippon Back Basic 1500 | E10: шт | F10: 1 | G10: 17000 | H10: =F10*G10 -> 17000 | I10: nix.ru — 16 690
A11: 8 | B11: Периферия | C11: Клавиатура, мышь, гарнитура | D11: Logitech | E11: компл | F11: 1 | G11: 15000 | H11: =F11*G11 -> 15000 | I11: оценка
A12: 9 | B12: Точка доступа WiFi 6 в депо | C12: Автовыгрузка смен при заезде | D12: TP-Link Omada EAP670 + PoE | E12: шт | F12: 1 | G12: 18000 | H12: =F12*G12 -> 18000 | I12: tplink.com.ru — 17 090
A13: 10 | B13: Калибровочные мишени | D13: шахматка + ChArUco, ПВХ 5 мм | E13: компл | F13: 1 | G13: 8000 | H13: =F13*G13 -> 8000 | I13: оценка
A14: 11 | B14: Рейка дорожная 3 м с клином, С ПОВЕРКОЙ | C14: Юридически значимый ground truth (акты по ГОСТ Р 50597) | D14: РДУ «Кондор» | E14: шт | F14: 1 | G14: 58000 | H14: =F14*G14 -> 58000 | I14: rusgeocom.ru — 58 000 | J14: Ежегодное продление поверки ~8 тыс.
A15: 12 | B15: Дальномер + мерный инструмент | D15: Bosch GLM 50 + рулетка/линейка | E15: компл | F15: 1 | G15: 15000 | H15: =F15*G15 -> 15000 | I15: оценка
A16: 13 | B16: Комплект безопасности | D16: 2 жилета + 4 конуса + знак | E16: компл | F16: 2 | G16: 8000 | H16: =F16*G16 -> 16000 | I16: оценка
A17: 14 | B17: Внешний SSD 2 ТБ USB-C | C17: Резервный перенос данных | D17: Samsung T7 | E17: шт | F17: 1 | G17: 20000 | H17: =F17*G17 -> 20000 | I17: оценка 18–22 тыс.
B18: ИТОГО | H18: =H4+H5+H6+H7+H8+H9+H10+H11+H12+H13+H14+H15+H16+H17 -> 919000
B19: Резерв на непредвиденные, 10% | H19: =ROUND(H18*0.1,-3) -> 92000
B20: ВСЕГО с резервом | H20: =H18+H19 -> 1011000

Sheet В3_Риг
A1: Вариант 3 «Риг» — 3 машины (1 с промкамерами + 2 с регистраторами), ориентир 1,8 млн ₽
A2: Единственный вариант, отвечающий на главный исследовательский вопрос проекта: пилот двухвидовой глубины (режим E) на настоящем калиброванном риге с global shutter. Плюс покрытие сети тремя машинами.
A3: № | B3: Наименование | C3: Назначение / обоснование | D3: Модель-пример | E3: Ед. | F3: Кол-во | G3: Цена за ед., ₽ | H3: Сумма, ₽ | I3: Ориентир цены (июль 2026) | J3: Примечание
B4: БЛОК А. Риговая машина №1 — промкамеры global shutter (пилот измерений глубины)
A5: 1 | B5: Промкамера 8,9 Мп global shutter GigE | C5: Перед + зад; глобальный затвор обязателен для измерений на ходу (на 60 км/ч смаз 17 мм/мс) | D5: Hikrobot MV-CS089-10GC (Sony IMX267, 1") | E5: шт | F5: 2 | G5: 110000 | H5: =F5*G5 -> 220000 | I5: оценка 100–140 тыс. (дистр.: mallenom.ru, digitoria.ru; 5 Мп GS — 71 638) | J5: НЕ брать «20 Мп» на IMX183/226 — rolling shutter
A6: 2 | B6: Объектив C-mount 12 Мп | C6: Полоса дороги с дистанций 2,5–8 м | D6: Hikrobot MVL-KF1228M-12MP | E6: шт | F6: 2 | G6: 30000 | H6: =F6*G6 -> 60000 | I6: оценка 25–45 тыс.
A7: 3 | B7: Термокожух с обогревом | C7: Всесезонная работа | D7: Wizebox (РФ) | E7: шт | F7: 2 | G7: 15000 | H7: =F7*G7 -> 30000 | I7: оценка 10–25 тыс. (wizebox.ru)
A8: 4 | B8: Бортовой мини-ПК + PoE-инжекторы | C8: Съёмка по дистанции, запись кадров, синхронизация PPS. Компактный x86 вместо транспортного Neousys (—450 тыс.) | D8: мини-ПК x86 (Ryzen 7/Core i5) + 2×PoE+ | E8: компл | F8: 1 | G8: 115000 | H8: =F8*G8 -> 115000 | I8: оценка | J8: Компромисс варианта: потребительское исполнение, питание через DC-UPS
A9: 5 | B9: DC-UPS / питание 12 В с задержкой выключения | C9: Корректное завершение записи при глушении | D9: Mini-Box OpenUPS / аналог | E9: шт | F9: 1 | G9: 25000 | H9: =F9*G9 -> 25000 | I9: оценка 15–30 тыс.
A10: 6 | B10: NVMe SSD 2 ТБ | C10: Буфер смен | D10: Samsung 990 Pro 2TB | E10: шт | F10: 1 | G10: 18000 | H10: =F10*G10 -> 18000 | I10: оценка
A11: 7 | B11: GNSS RTK-модуль с IMU и PPS + survey-антенна | C11: Геопривязка + первичный тангаж; PPS триггерит кадры по дистанции | D11: u-blox ZED-F9R + антенна | E11: компл | F11: 1 | G11: 70000 | H11: =F11*G11 -> 70000 | I11: оценка 55–75 тыс.
A12: 8 | B12: Крепёж: платформа, кронштейны, виброразвязка | C12: Жёсткий риг = постоянный эталон масштаба | D12: экспедиционная платформа + виброопоры | E12: компл | F12: 1 | G12: 30000 | H12: =F12*G12 -> 30000 | I12: оценка
A13: 9 | B13: Кабели M12/GigE, PoE, гермовводы | E13: компл | F13: 1 | G13: 20000 | H13: =F13*G13 -> 20000 | I13: оценка
A14: 10 | B14: Монтаж и калибровка рига | C14: Интринзики (шахматка), высота, тангаж | D14: работы | E14: усл | F14: 1 | G14: 30000 | H14: =F14*G14 -> 30000 | I14: оценка | J14: Повторять после каждого демонтажа
B15: БЛОК Б. Машины №2–3 — видеорегистраторы (покрытие сети)
A16: 11 | B16: Видеорегистратор BlackVue DR970X-2CH | C16: Детекция и реестр на двух дополнительных маршрутах | D16: BlackVue DR970X-2CH | E16: шт | F16: 2 | G16: 86000 | H16: =F16*G16 -> 172000 | I16: alarm.ru — 85 490
A17: 12 | B17: microSD 256 ГБ + проводка + установка | E17: компл | F17: 2 | G17: 15000 | H17: =F17*G17 -> 30000 | I17: оценка
A18: 13 | B18: GNSS ZED-F9P + антенна | C18: Геопривязка кадров | D18: u-blox ZED-F9P | E18: компл | F18: 2 | G18: 30000 | H18: =F18*G18 -> 60000 | I18: asiaoptom.com — 20–35 тыс.
B19: БЛОК В. Сервер и АРМ
A20: 14 | B20: Сервер-ПК | C20: Конвейер по 3 машинам, БД, веб, дообучение; фотограмметрия рига | D20: Ryzen 9 9950X / 96 ГБ DDR5 / RTX 5070 Ti 16 ГБ / NVMe 4 ТБ / 2×20 ТБ HDD | E20: шт | F20: 1 | G20: 450000 | H20: =F20*G20 -> 450000 | I20: RTX 5070 Ti от 97 990 (regard.ru); HDD/RAM — оценка при дефиците 2026
A21: 15 | B21: Монитор 27" 4K IPS | D21: LG 27UP650 | E21: шт | F21: 2 | G21: 45000 | H21: =F21*G21 -> 90000 | I21: оценка
A22: 16 | B22: ИБП 1500 ВА | D22: Ippon Back Basic 1500 | E22: шт | F22: 1 | G22: 17000 | H22: =F22*G22 -> 17000 | I22: nix.ru — 16 690
A23: 17 | B23: Периферия | D23: Logitech + гарнитура | E23: компл | F23: 1 | G23: 15000 | H23: =F23*G23 -> 15000 | I23: оценка
A24: 18 | B24: Точка доступа WiFi 6 в депо | C24: Автовыгрузка (риг: 10–15 ГБ/смена кадрами) | D24: TP-Link EAP670 | E24: шт | F24: 1 | G24: 18000 | H24: =F24*G24 -> 18000 | I24: tplink.com.ru — 17 090
B25: БЛОК Г. Калибровка и контрольные замеры
A26: 19 | B26: Калибровочные мишени (вкл. ChArUco А1 на алюкобонде) | D26: печать АКП/ПВХ | E26: компл | F26: 1 | G26: 10000 | H26: =F26*G26 -> 10000 | I26: оценка
A27: 20 | B27: Рейка дорожная 3 м с клином, С ПОВЕРКОЙ | C27: Ground truth глубины для пилота рига и актов | D27: РДУ «Кондор» | E27: шт | F27: 1 | G27: 58000 | H27: =F27*G27 -> 58000 | I27: rusgeocom.ru — 58 000
A28: 21 | B28: Дальномер + мерный инструмент | D28: Bosch GLM 50 / ADA + рулетки | E28: компл | F28: 1 | G28: 20000 | H28: =F28*G28 -> 20000 | I28: оценка
A29: 22 | B29: Комплект безопасности | D29: жилеты + конусы + знак | E29: компл | F29: 3 | G29: 8000 | H29: =F29*G29 -> 24000 | I29: оценка
A30: 23 | B30: Внешний SSD 2 ТБ USB-C | D30: Samsung T7 | E30: шт | F30: 1 | G30: 20000 | H30: =F30*G30 -> 20000 | I30: оценка
B31: ИТОГО | H31: =H5+H6+H7+H8+H9+H10+H11+H12+H13+H14+H16+H17+H18+H20+H21+H22+H23+H24+H26+H27+H28+H29+H30 -> 1602000
B32: Резерв на непредвиденные, 10% | H32: =ROUND(H31*0.1,-3) -> 160000
B33: ВСЕГО с резервом | H33: =H31+H32 -> 1762000

Sheet OPEX_Опции
A1: OPEX и опции апгрейда
A2: Строка «ИТОГО» на этом листе — сумма всех строк листа, приведена справочно и в бюджет вариантов не входит.
A3: № | B3: Наименование | C3: Назначение / обоснование | D3: Модель-пример | E3: Ед. | F3: Кол-во | G3: Цена за ед., ₽ | H3: Сумма, ₽ | I3: Ориентир цены (июль 2026) | J3: Примечание
B4: OPEX (в год)
A5: 1 | B5: RTK-поправки NTRIP (по потребности) | C5: Нужны только для см-точности привязки; метровая точность GNSS — бесплатно. Для пилота можно не подключать | D5: EFT-CORS (Ростов-на-Дону) | E5: приёмник | F5: 1 | G5: 50400 | H5: =F5*G5 -> 50400 | I5: eft-cors.ru — 50 400 ₽/год | J5: SmartNet — 41 900 ₽/год; своя база (см. опции) обнуляет
A6: 2 | B6: Продление поверки рейки | E6: год | F6: 1 | G6: 8000 | H6: =F6*G6 -> 8000 | I6: оценка
A7: 3 | B7: Связь LTE (если выгрузка с маршрута) | D7: SIM М2М | E7: шт/год | F7: 1 | G7: 8400 | H7: =F7*G7 -> 8400 | I7: оценка 700 ₽/мес | J7: Опция
B8: Опции апгрейда (в итоги вариантов не входят)
A9: 4 | B9: Собственная базовая станция RTK | C9: Бесплатные поправки всем машинам в радиусе ~30–50 км | D9: ZED-F9P + антенна на крыше офиса | E9: компл | F9: 1 | G9: 30000 | H9: =F9*G9 -> 30000 | I9: оценка | J9: У EFT-CORS есть схема «база у вас — 2 доступа бесплатно»
A10: 5 | B10: Апгрейд GPU сервера до RTX 5090 32 ГБ | C10: Быстрое дообучение, запас на парк | D10: RTX 5090 | E10: шт | F10: 1 | G10: 425000 | H10: =F10*G10 -> 425000 | I10: regard.ru — от 424 990 | J10: Замена 5070 Ti: доплата ~330 тыс.
A11: 6 | B11: Транспортный бортовой ПК вместо мини-ПК | C11: Вибростойкость, ignition, −40…+70 °C | D11: Neousys Nuvo-7250VTC | E11: шт | F11: 1 | G11: 550000 | H11: =F11*G11 -> 550000 | I11: оценка 450–700 тыс. (nnz-ipc.ru) | J11: Для тиража рига
A12: 7 | B12: Камеры 12,3 Мп вместо 8,9 Мп | C12: ~1 мм/px в рабочей зоне | D12: Hikrobot MV-CS120-10GC | E12: шт | F12: 2 | G12: 160000 | H12: =F12*G12 -> 320000 | I12: оценка 130–180 тыс. | J12: Доплата ~50 тыс./камера
A13: 8 | B13: Дальномер с поверкой (IP65) | C13: Если замеры дистанций идут в протоколы | D13: Leica DISTO X3 | E13: шт | F13: 1 | G13: 49000 | H13: =F13*G13 -> 49000 | I13: geooptic.ru — 47 300 + поверка
A14: 9 | B14: NAS 4 отсека + 2×16 ТБ | C14: Выделенный архив и бэкап БД | D14: QNAP/Synology 4-bay | E14: компл | F14: 1 | G14: 170000 | H14: =F14*G14 -> 170000 | I14: оценка
A15: 10 | B15: Ещё одна регистраторная машина | C15: Расширение покрытия | D15: BlackVue + SD + проводка + F9P | E15: компл | F15: 1 | G15: 131000 | H15: =F15*G15 -> 131000 | I15: по ценам В2
A16: 11 | B16: Доп. АРМ оператора (ПК без GPU + монитор) | C16: Если разметчик и оператор — разные люди | D16: Ryzen 5 / 32 ГБ + 27" 4K | E16: компл | F16: 1 | G16: 150000 | H16: =F16*G16 -> 150000 | I16: оценка
B17: ИТОГО | H17: =H5+H6+H7+H9+H10+H11+H12+H13+H14+H15+H16 -> 1891800
B18: Резерв на непредвиденные, 10% | H18: =ROUND(H17*0.1,-3) -> 189000
B19: ВСЕГО с резервом | H19: =H17+H18 -> 2080800
