Workbook

Sheet Сводка
A1: Спецификация оборудования: система автоматического учёта дорожных дефектов
A2: Цены ориентировочные: розница РФ, июль 2026, с НДС. Синим — редактируемые значения (цены, количества), чёрным — формулы, зелёным — ссылки на листы разделов, жёлтая заливка — ключевой параметр. Перед закупкой актуализировать цены по счетам поставщиков (память, накопители и GPU волатильны).
A4: ПАРАМЕТРЫ
A5: Количество бортовых комплектов (машин) | B5: 3 | C5: Меняйте здесь — разделы 3, 4, 5, 7 пересчитаются автоматически
A7: CAPEX — ОСНОВНОЙ ВАРИАНТ (А: промышленные камеры)
A8: 1. Сервер обработки (покупка) | B8: =1_Сервер!H16 -> 3835000 | C8: Раздел 1; альтернатива-аренда — внизу листа раздела
A9: 2. АРМ оператора | B9: =2_АРМ!H8 -> 658000 | C9: Раздел 2
A10: 3. Бортовые комплексы — вариант А (промкамеры) | B10: =3_Борт_А!H13 -> 3687000 | C10: Раздел 3; кол-во машин — параметр B5
A11: 4. Геолокация (борт + базовая станция RTK) | B11: =5_Геолокация!H8 -> 351000 | C11: Раздел 5
A12: 5. Депо: сеть выгрузки и хранение | B12: =6_Депо_СХД!H10 -> 1145000 | C12: Раздел 6
A13: 6. Калибровка и контрольные замеры (GT) | B13: =7_Калибровка!H10 -> 273000 | C13: Раздел 7
A14: ИТОГО, вариант А | B14: =SUM(B8:B13) -> 9949000
A15: Резерв на непредвиденные расходы, 10% | B15: =ROUND(B14*0.1,-3) -> 995000 | C15: Курсовые колебания, доставка, мелочёвка монтажа
A16: ВСЕГО с резервом, вариант А | B16: =B14+B15 -> 10944000
A18: СПРАВОЧНО — ВАРИАНТ Б (видеорегистраторы вместо промкамер)
A19: Бортовые комплексы — вариант Б | B19: =4_Борт_Б!H8 -> 324000 | C19: Только пилот/скрининг: без global shutter и метрологии — измерения глубины не обеспечивает
A20: ИТОГО, вариант Б (замена раздела 3 на регистраторы) | B20: =B14-B10+B19 -> 6586000 | C20: Экономия видна, но вариант закрывает только детекцию
A21: ВСЕГО с резервом 10%, вариант Б | B21: =B20+ROUND(B20*0.1,-3) -> 7245000
A23: OPEX, В ГОД
A24: RTK-поправки NTRIP (EFT-CORS, на парк) | B24: =5_Геолокация!H11 -> 151200 | C24: Обнуляется при собственной базовой станции (заложена в разделе 5)
A25: Связь LTE (3 SIM, опция) | B25: 25000
A26: Ежегодные поверки (рейки, дальномер) | B26: 15000
A27: ИТОГО OPEX/год | B27: =B24+B25+B26 -> 191200 | C27: Без электроэнергии/интернета площадки и без аренды сервера
A29: Аренда GPU-сервера вместо покупки (справочно) | B29: 50–150 тыс. ₽/мес | C29: Разумно на период пилота: immers.cloud/selectel; детали — лист «1_Сервер»

Sheet 1_Сервер
A1: Раздел 1. Сервер обработки (покупка, on-prem)
A2: Один узел на организацию. Обработка near-real-time: скрининг YOLO по всем кадрам → гео-группировка сцен → полный пайплайн → реестр дефектов (PostGIS) → уведомления. Аренда — см. блок внизу листа.
A3: № | B3: Наименование | C3: Назначение в системе / обоснование | D3: Модель-пример | E3: Ед. | F3: Кол-во | G3: Цена за ед., ₽ | H3: Сумма, ₽ | I3: Ориентир цены (июль 2026) | J3: Примечание
A4: 1 | B4: Серверная платформа 2U/4U под 2×GPU | C4: Единый узел обработки: приём кадров, скрининг-детекция, полный пайплайн, БД, веб-интерфейс. Резерв слота под второй GPU. 2 БП ≥2 кВт, IPMI | D4: Supermicro (новый барбон) / РФ-сборка OpenYard, Aquarius | E4: шт | F4: 1 | G4: 1000000 | H4: =F4*G4 -> 1000000 | I4: оценка 800 тыс.–1,2 млн (новые «по запросу»; б/у 2U от 350 тыс., ittelo.ru) | J4: Параллельный импорт либо РФ-вендор; уточнить конфигурацию у 2–3 поставщиков
A5: 2 | B5: Процессор AMD EPYC 9354 (32 ядра SP5) | C5: COLMAP/OpenMVS и сегментация — CPU-ёмкие этапы конвейера; 32 ядра держат парк из 3 машин | D5: AMD EPYC 9354 OEM | E5: шт | F5: 1 | G5: 225000 | H5: =F5*G5 -> 225000 | I5: serverflow.ru — 222 700 (в наличии) | J5: Разброс каналов 128–225 тыс.
A6: 3 | B6: ОЗУ DDR5 ECC RDIMM 256 ГБ (8×32) | C6: Очереди кадров 4K, PostGIS, дообучение YOLO, фотограмметрия | D6: SK Hynix 32GB DDR5-4800 RDIMM ×8 | E6: компл | F6: 1 | G6: 520000 | H6: =F6*G6 -> 520000 | I6: serverflow.ru — 56–75 тыс./модуль | J6: Цены DRAM 2026 аномально высоки (дефицит из-за ИИ) — перепроверить перед закупкой
A7: 4 | B7: GPU NVIDIA RTX 6000 Ada 48 ГБ | C7: Скрининг тысяч кадров/смену, дообучение детектора, ускорение фотограмметрии. Серверное исполнение (blower, ECC) | D7: NVIDIA RTX 6000 Ada Generation 48GB | E7: шт | F7: 1 | G7: 840000 | H7: =F7*G7 -> 840000 | I7: servermall.ru — 838 656; L40S — 763 900 (t-bazar.ru) | J7: Альтернатива: 2×RTX 5090 32 ГБ (~425 тыс./шт, regard.ru) — дешевле за FLOPS, но потребительское исполнение
A8: 5 | B8: СХД «горячая»: NVMe U.2 3,84 ТБ, RAID1 | C8: БД PostGIS + горячие данные конвейера (кадры в обработке) | D8: Samsung PM9A3 3.84TB U.2 ×2 | E8: шт | F8: 2 | G8: 205000 | H8: =F8*G8 -> 410000 | I8: serverflow.ru — 189–220 тыс./шт | J8: Enterprise-класс с защитой по питанию
A9: 6 | B9: СХД архивная: HDD 24 ТБ, RAID6 | C9: Архив исходных кадров и оверлеев (~10–15 ГБ/смена с машины) | D9: Seagate Exos X24 24TB ×4 | E9: шт | F9: 4 | G9: 120000 | H9: =F9*G9 -> 480000 | I9: nix.ru — 120 223 (офиц.); маркетплейсы 65–80 тыс. (риск канала) | J9: ≈44 ТБ полезной ёмкости в RAID6; расширяется до 8 дисков
A10: 7 | B10: HBA/RAID-контроллер + кабели | C10: Подключение U.2/SATA-корзин | D10: Broadcom 9500-8i | E10: шт | F10: 1 | G10: 60000 | H10: =F10*G10 -> 60000 | I10: оценка
A11: 8 | B11: Сетевой адаптер 10GbE SFP+ | C11: Быстрый приём выгрузки из депо и связь с NAS | D11: Intel X710-DA2 | E11: шт | F11: 1 | G11: 45000 | H11: =F11*G11 -> 45000 | I11: оценка | J11: Если нет на плате платформы
A12: 9 | B12: ИБП online 3 кВА, стоечный | C12: Двойное преобразование; защита БД от сбоев питания | D12: Ippon Innova RT 33 3000 / Powercom VGD | E12: шт | F12: 1 | G12: 100000 | H12: =F12*G12 -> 100000 | I12: оценка 70–130 тыс. (башенный PowerMan Online 3000 — 36 261, nix.ru)
A13: 10 | B13: Серверный шкаф 22U + PDU | C13: Размещение сервера, ИБП, коммутатора, NAS | D13: ЦМО/SYSMATRIX/W&T 22U 600×800 + PDU 8×C13 | E13: компл | F13: 1 | G13: 60000 | H13: =F13*G13 -> 60000 | I13: оценка (шкаф 25–60 тыс., vseinstrumenti.ru; PDU 8–25 тыс.)
A14: 11 | B14: Коммутатор 10GbE | C14: Ядро сети: сервер ↔ NAS ↔ депо-сеть | D14: MikroTik CRS309-1G-8S+IN | E14: шт | F14: 1 | G14: 45000 | H14: =F14*G14 -> 45000 | I14: оценка 35–45 тыс. (MSRP $269 + наценка)
A15: 12 | B15: Монтаж, пусконаладка, ОС и окружение | C15: Сборка, ОС Linux, PostgreSQL+PostGIS, очереди, развёртывание движка | D15: работы | E15: усл | F15: 1 | G15: 50000 | H15: =F15*G15 -> 50000 | I15: оценка | J15: Если делаете сами — исключить строку
B16: ИТОГО по разделу | H16: =SUM(H4:H15) -> 3835000
B18: СПРАВОЧНО: аренда GPU-сервера вместо покупки (OPEX)
B19: Аренда: сервер с 1×RTX 4090/5090 | C19: Достаточно для пилота и старта эксплуатации | D19: immers.cloud / selectel.ru | E19: мес | G19: 50000 | I19: immers.cloud — от ~40–60 тыс. ₽/мес (при предоплате)
B20: Аренда: сервер с L40S/A100 | C20: Запас под тираж и постоянное дообучение | D20: selectel.ru | E20: мес | G20: 150000 | I20: оценка 100–200 тыс. ₽/мес

Sheet 2_АРМ
A1: Раздел 2. Автоматизированное рабочее место оператора
A2: Оператор принимает результаты конвейера, ведёт реестр, размечает eval-набор для замера качества детекции (docs/EVAL.md).
A3: № | B3: Наименование | C3: Назначение в системе / обоснование | D3: Модель-пример | E3: Ед. | F3: Кол-во | G3: Цена за ед., ₽ | H3: Сумма, ₽ | I3: Ориентир цены (июль 2026) | J3: Примечание
A4: 1 | B4: Рабочая станция оператора | C4: Веб-дашборд, контроль качества, разметка датасетов (X-AnyLabeling), локальный инференс и прогон моделей | D4: Ryzen 9 9950X / 64 ГБ DDR5 / RTX 5080 16 ГБ / NVMe 2 ТБ + 4 ТБ | E4: шт | F4: 1 | G4: 460000 | H4: =F4*G4 -> 460000 | I4: digital-razor.ru — 400–471 тыс.; самосбор ~380–430 тыс. | J4: С RTX 5070 Ti — экономия ~50 тыс. без потери для разметки
A5: 2 | B5: Монитор 27" 4K IPS | C5: Разметка мелких дефектов (трещины 1–2 px) требует 4K; второй экран — карта/реестр | D5: Dell P2723QE / LG 27UP650 | E5: шт | F5: 2 | G5: 55000 | H5: =F5*G5 -> 110000 | I5: оценка 35–60 тыс. (lg.com/ru, DNS)
A6: 3 | B6: ИБП 1500 ВА, чистый синус | C6: Защита АРМ | D6: Ippon Smart Winner II 1550 | E6: шт | F6: 1 | G6: 38000 | H6: =F6*G6 -> 38000 | I6: оценка (Back Basic 1500 — 16 690, nix.ru)
A7: 4 | B7: Периферия | C7: Клавиатура, мышь, гарнитура, веб-камера | D7: Logitech MX Keys S + MX Master 3S + гарнитура | E7: компл | F7: 1 | G7: 50000 | H7: =F7*G7 -> 50000 | I7: оценка 40–55 тыс. | J7: Бюджетный комплект ~15–20 тыс.
B8: ИТОГО по разделу | H8: =SUM(H4:H7) -> 658000

Sheet 3_Борт_А
A1: Раздел 3. Бортовой комплекс — вариант А: промышленные камеры (основной)
A2: Количество машин задаётся на листе «Сводка» (B5). Съёмка непрерывная по дистанции, обработка на сервере — на борту только запись.
A3: № | B3: Наименование | C3: Назначение в системе / обоснование | D3: Модель-пример | E3: Ед. | F3: Кол-во | G3: Цена за ед., ₽ | H3: Сумма, ₽ | I3: Ориентир цены (июль 2026) | J3: Примечание
A4: 1 | B4: Промышленная камера 12,3 Мп, global shutter, GigE | C4: Передняя + задняя съёмка (решение проекта: задняя камера обязательна для two-view глубины). Global shutter обязателен: на 60 км/ч смаз 17 мм/мс, короткая выдержка без геометрических искажений | D4: Hikrobot MV-CS120-10GC (Sony IMX253, 1.1") | E4: шт | F4: =2*Сводка!$B$5 -> 6 | G4: 160000 | H4: =F4*G4 -> 960000 | I4: оценка 130–180 тыс. (дистр.: mallenom.ru, effort-group.ru; 5 Мп GS — 71 638, digitoria.ru) | J4: 2 шт/машину. НЕ брать «дешёвые 20 Мп» на IMX183/IMX226 — там rolling shutter
A5: 2 | B5: Объектив C-mount 12 Мп, 1.1" | C5: Фокусное 8–12 мм: полоса дороги целиком с дистанций 2,5–8 м | D5: Hikrobot MVL-KF1228M-12MP (опция: Computar V1228-MPY) | E5: шт | F5: =2*Сводка!$B$5 -> 6 | G5: 40000 | H5: =F5*G5 -> 240000 | I5: оценка 25–45 тыс.; Computar 80–120 тыс.
A6: 3 | B6: Термокожух IP66/67 с обогревом + салазки | C6: Всесезонная работа снаружи кузова | D6: Wizebox (РФ) / Hikvision DS-1331HZ-H | E6: шт | F6: =2*Сводка!$B$5 -> 6 | G6: 22000 | H6: =F6*G6 -> 132000 | I6: оценка 10–25 тыс. (wizebox.ru, satro-paladin.com)
A7: 4 | B7: Бортовой компьютер транспортного исполнения | C7: Съёмка по дистанции (кадр каждые 3–5 м по GNSS), запись кадров с метаданными, PPS-синхронизация «кадр↔координата», буфер смены. Питание 8–48 В, ignition control, PoE+ для камер | D7: Neousys Nuvo-7250VTC (встроенный ИБП на суперконденсаторах) | E7: шт | F7: =1*Сводка!$B$5 -> 3 | G7: 550000 | H7: =F7*G7 -> 1650000 | I7: оценка 450–700 тыс. (nnz-ipc.ru, ipc2u.ru — по запросу); якорь: Jetson AGX Orin 64GB devkit — 413 310 (compacttool.ru) | J7: Срок поставки 6–12 недель — заказывать первым
A8: 5 | B8: Накопитель NVMe 4 ТБ | C8: Буфер смены: 10–15 ГБ/смена + запас на неделю | D8: Samsung 990 Pro 4TB | E8: шт | F8: =1*Сводка!$B$5 -> 3 | G8: 70000 | H8: =F8*G8 -> 210000 | I8: regard.ru — 69 990
A9: 6 | B9: Крепёж: платформа, кронштейны, виброразвязка | C9: Жёсткая фиксация рига — база калибровки (высота, тангаж). Виброразвязка только высокочастотная | D9: Экспедиционная платформа + кронштейны + виброопоры | E9: компл | F9: =1*Сводка!$B$5 -> 3 | G9: 50000 | H9: =F9*G9 -> 150000 | I9: оценка 30–70 тыс. | J9: Жёсткость важнее демпфирования
A10: 7 | B10: Кабели GigE/M12, PoE, гермовводы, проводка | C10: Подключение камер и питания | D10: промышленные Cat6A M12, PoE-инжекторы | E10: компл | F10: =1*Сводка!$B$5 -> 3 | G10: 30000 | H10: =F10*G10 -> 90000 | I10: оценка 15–40 тыс.
A11: 8 | B11: LTE-роутер (опция оперативной выгрузки) | C11: Выгрузка приоритетных сцен с маршрута; основной канал — WiFi в депо | D11: iRZ / Kroks Rt-Cse (РФ) | E11: шт | F11: =1*Сводка!$B$5 -> 3 | G11: 25000 | H11: =F11*G11 -> 75000 | I11: оценка 15–30 тыс. (irz.net, kroks.ru) | J11: Teltonika RUTX11 — 45 771 (i-teh.com), но вендор ушёл из РФ
A12: 9 | B12: Монтаж на автомобиль, юстировка, калибровка рига | C12: Интринзики (шахматка), высота, тангаж — риг становится постоянным эталоном масштаба | D12: работы | E12: усл | F12: =1*Сводка!$B$5 -> 3 | G12: 60000 | H12: =F12*G12 -> 180000 | I12: оценка | J12: Повторная калибровка после каждого демонтажа
B13: ИТОГО по разделу | H13: =SUM(H4:H12) -> 3687000

Sheet 4_Борт_Б
A1: Раздел 4. Бортовой комплекс — вариант Б: видеорегистратор (пилот/бюджет)
A2: Альтернатива варианту А для сравнения бюджета. Годится для пилота детекции и наработки датасета; метрологические задачи (риговый масштаб, two-view глубина) НЕ решает.
A3: № | B3: Наименование | C3: Назначение в системе / обоснование | D3: Модель-пример | E3: Ед. | F3: Кол-во | G3: Цена за ед., ₽ | H3: Сумма, ₽ | I3: Ориентир цены (июль 2026) | J3: Примечание
A4: 1 | B4: Видеорегистратор 2-канальный 4K+FHD с GPS | C4: Бюджетная фиксация перед/зад для пилота и скрининга | D4: BlackVue DR970X-2CH | E4: шт | F4: =1*Сводка!$B$5 -> 3 | G4: 86000 | H4: =F4*G4 -> 258000 | I4: alarm.ru — 85 490 (в наличии) | J4: Ограничения: rolling shutter, сжатие H.265 (теряет мм-текстуру асфальта), задняя камера только FHD, съёмка по времени, автоэкспозиция. Для измерений глубины НЕ пригоден
A5: 2 | B5: Карта microSD 256 ГБ high-endurance | C5: Носитель записи | D5: Samsung PRO Endurance / SanDisk Max Endurance | E5: шт | F5: =1*Сводка!$B$5 -> 3 | G5: 5000 | H5: =F5*G5 -> 15000 | I5: оценка
A6: 3 | B6: Комплект скрытой проводки + установка | C6: Питание от бортсети с защитой АКБ | D6: hardwire kit + работы | E6: компл | F6: =1*Сводка!$B$5 -> 3 | G6: 15000 | H6: =F6*G6 -> 45000 | I6: оценка
A7: 4 | B7: GPS-логгер с PPS (резерв привязки времени) | C7: Дублирующий трек и точное время | D7: u-blox NEO-M10 с антенной | E7: шт | F7: =1*Сводка!$B$5 -> 3 | G7: 2000 | H7: =F7*G7 -> 6000 | I7: amperkot.ru — 1 425
B8: ИТОГО по разделу | H8: =SUM(H4:H7) -> 324000

Sheet 5_Геолокация
A1: Раздел 5. Оборудование геопривязки (CAPEX)
A2: Без геопривязки не работают: группировка кадров в сцены дефектов, дедупликация повторных проездов, назначение ответственных по зонам. Подписки NTRIP — в OPEX (см. Сводку).
A3: № | B3: Наименование | C3: Назначение в системе / обоснование | D3: Модель-пример | E3: Ед. | F3: Кол-во | G3: Цена за ед., ₽ | H3: Сумма, ₽ | I3: Ориентир цены (июль 2026) | J3: Примечание
A4: 1 | B4: GNSS RTK-модуль с IMU и PPS | C4: Геопривязка каждого кадра (координата, курс, время), RTK 1–2 см при поправках, dead reckoning в «каньонах» застройки; IMU — первичное уточнение тангажа | D4: u-blox ZED-F9R (плата ArduSimple simpleRTK2B/SparkFun) | E4: шт | F4: =1*Сводка!$B$5 -> 3 | G4: 55000 | H4: =F4*G4 -> 165000 | I4: оценка 40–60 тыс. (параллельный импорт; attal.ru — под заказ) | J4: PPS-выход синхронизирует затвор камер с координатой
A5: 2 | B5: GNSS-антенна survey-grade, магнитная | C5: Многодиапазонная L1/L2/L5, IP67, на крышу | D5: Harxon HX-CSX601A / аналог | E5: шт | F5: =1*Сводка!$B$5 -> 3 | G5: 25000 | H5: =F5*G5 -> 75000 | I5: оценка 15–35 тыс. (geodetika.ru)
A6: 3 | B6: Резервный GPS-логгер с PPS | C6: Независимый трек и время на случай отказа основного | D6: u-blox NEO-M10 с антенной | E6: шт | F6: =1*Сводка!$B$5 -> 3 | G6: 2000 | H6: =F6*G6 -> 6000 | I6: amperkot.ru — 1 425
A7: 4 | B7: Собственная базовая станция RTK (на офис/депо) | C7: Бесплатные поправки для всех машин в радиусе ~30–50 км; исключает подписки NTRIP | D7: Emlid Reach M2 + антенна | E7: компл | F7: 1 | G7: 105000 | H7: =F7*G7 -> 105000 | I7: geobond.ru — Reach M2 89 000 + антенна ~15 тыс. | J7: У EFT-CORS есть схема «база у вас — 2 доступа бесплатно навсегда»
B8: ИТОГО по разделу | H8: =SUM(H4:H7) -> 351000
B10: OPEX: RTK-поправки NTRIP (если не ставить свою базу)
B11: Подписка EFT-CORS (покрывает Ростов-на-Дону, офис: Б. Садовая 89) | C11: 50 400 ₽/год на приёмник (30 240 — для приёмников EFT); SmartNet — 41 900 ₽/год | D11: eft-cors.ru/prices; smartnetrtk.ru | F11: =Сводка!$B$5 -> 3 | G11: 50400 | H11: =F11*G11 -> 151200 | J11: ₽/год на парк; при своей базе = 0

Sheet 6_Депо_СХД
A1: Раздел 6. Депо: сеть выгрузки и хранение
A2: Основной канал выгрузки — WiFi в депо (решение проекта: LTE — опция, не базовый канал).
A3: № | B3: Наименование | C3: Назначение в системе / обоснование | D3: Модель-пример | E3: Ед. | F3: Кол-во | G3: Цена за ед., ₽ | H3: Сумма, ₽ | I3: Ориентир цены (июль 2026) | J3: Примечание
A4: 1 | B4: NAS 8 отсеков | C4: Приём выгрузки со всех машин, долговременный архив, резервная копия БД | D4: QNAP TS-873A-8G / Synology DS1821+ | E4: шт | F4: 1 | G4: 180000 | H4: =F4*G4 -> 180000 | I4: оценка 150–200 тыс. (Synology DS1823xs+ — 280–330 тыс., параллельный импорт)
A5: 2 | B5: HDD NAS/Enterprise 24 ТБ | C5: 8×24 ТБ в RAID6 ≈ 130 ТБ полезной ёмкости — годы архива при 30–45 ГБ/день с парка | D5: Seagate IronWolf Pro 24TB / Exos X24 | E5: шт | F5: 8 | G5: 110000 | H5: =F5*G5 -> 880000 | I5: nix.ru — IronWolf Pro 104 263, Exos 120 223; маркетплейсы 65–80 тыс. | J5: Цены HDD в 2026 удвоились — фиксировать счётом
A6: 3 | B6: Точка доступа WiFi 6 в депо | C6: Автовыгрузка смены (10–15 ГБ) при заезде — минуты | D6: TP-Link Omada EAP670 + PoE | E6: шт | F6: 1 | G6: 20000 | H6: =F6*G6 -> 20000 | I6: tplink.com.ru — 17 090; i-teh.com — 14 781
A7: 4 | B7: WiFi-мост на стоянку | C7: Если стоянка машин дальше зоны WiFi депо | D7: 2× TP-Link CPE710 | E7: компл | F7: 1 | G7: 20000 | H7: =F7*G7 -> 20000 | I7: оценка 16–20 тыс.
A8: 5 | B8: Коммутатор PoE Gigabit/2.5G, 8 портов | C8: Питание точек доступа, сеть депо | D8: TP-Link/Keenetic PoE+ | E8: шт | F8: 1 | G8: 25000 | H8: =F8*G8 -> 25000 | I8: оценка
A9: 6 | B9: Монтаж сети депо | C9: Кабельные трассы, настройка | D9: работы | E9: усл | F9: 1 | G9: 20000 | H9: =F9*G9 -> 20000 | I9: оценка
B10: ИТОГО по разделу | H10: =SUM(H4:H9) -> 1145000

Sheet 7_Калибровка
A1: Раздел 7. Калибровка и контрольные замеры (ground truth)
A2: Принцип проекта: сертифицируемые сантиметры — только от подтверждённого эталона. Рейка и мишени — источник ground truth и юридической значимости.
A3: № | B3: Наименование | C3: Назначение в системе / обоснование | D3: Модель-пример | E3: Ед. | F3: Кол-во | G3: Цена за ед., ₽ | H3: Сумма, ₽ | I3: Ориентир цены (июль 2026) | J3: Примечание
A4: 1 | B4: Калибровочные мишени | C4: Интринзики камер (шахматка) и маркерные доски ChArUco для режима D ручной досъёмки — метрический масштаб и позы кадров через PnP | D4: Шахматка А1 + ChArUco 2×А2 + 1×А1, УФ-печать на ПВХ 5 мм/алюкобонде, матовая ламинация | E4: компл | F4: 1 | G4: 15000 | H4: =F4*G4 -> 15000 | I4: оценка (лист ПВХ 3 мм — 1 390, poliservis.com; АКП А1 — 4,5–6,5 тыс.) | J4: Жёсткая основа обязательна — лист не должен «гулять»
A5: 2 | B5: Рейка дорожная 3 м с промерным клином, с поверкой | C5: Юридически значимый ground truth глубины: контрольные замеры 10–15 ям для валидации two-view (пилот, п. 3) и актирование по ГОСТ Р 50597 | D5: РДУ «Кондор» (ГОСТ 30412) | E5: шт | F5: 2 | G5: 58000 | H5: =F5*G5 -> 116000 | I5: rusgeocom.ru, laserstroy.ru — 58 000 с поверкой | J5: Поверка обязательна, если замеры идут в акты; ежегодное продление
A6: 3 | B6: Лазерный дальномер IP65 + поверка | C6: Дистанции съёмки, высота камер при калибровке | D6: Leica DISTO X3 | E6: шт | F6: 1 | G6: 49000 | H6: =F6*G6 -> 49000 | I6: geooptic.ru — 47 300 + поверка 1 000
A7: 4 | B7: Рулетки 5 м, линейки металлические (ГОСТ 427) | C7: Ручные замеры, высота рига | D7: Stanley/STAYER + линейка 500 мм | E7: компл | F7: 1 | G7: 3000 | H7: =F7*G7 -> 3000 | I7: оценка
A8: 5 | B8: Комплект безопасности на машину | C8: Работы на проезжей части при контрольных замерах | D8: 2 жилета + 4 конуса 520 мм с утяжелителем + знак | E8: компл | F8: =1*Сводка!$B$5 -> 3 | G8: 8000 | H8: =F8*G8 -> 24000 | I8: оценка (конус — 579–1 120, saturn.net/protect-market.ru)
A9: 6 | B9: Внешний SSD 2 ТБ USB-C | C9: Ручной перенос данных при недоступности WiFi/LTE | D9: Samsung T7/T9 2TB | E9: шт | F9: =1*Сводка!$B$5 -> 3 | G9: 22000 | H9: =F9*G9 -> 66000 | I9: оценка 18–30 тыс.
B10: ИТОГО по разделу | H10: =SUM(H4:H9) -> 273000

Sheet 8_Опции
A1: Раздел 8. Опции (НЕ входят в итоговую сумму)
A2: Позиции по итогам пилота или при масштабировании.
A3: № | B3: Наименование | C3: Назначение в системе / обоснование | D3: Модель-пример | E3: Ед. | F3: Кол-во | G3: Цена за ед., ₽ | H3: Сумма, ₽ | I3: Ориентир цены (июль 2026) | J3: Примечание
A4: 1 | B4: Второй GPU RTX 6000 Ada 48 ГБ | C4: Масштабирование: раздельные контуры инференса и дообучения | D4: NVIDIA RTX 6000 Ada | E4: шт | F4: 1 | G4: 840000 | H4: =F4*G4 -> 840000 | I4: servermall.ru | J4: Слот и питание в платформе заложены
A5: 2 | B5: Камеры 24,5 Мп global shutter вместо 12,3 Мп | C5: Выше детализация текстуры дна — запас точности фотограмметрии | D5: Hikrobot MV-CS230-10GC (IMX530) | E5: шт | F5: 6 | G5: 100000 | H5: =F5*G5 -> 600000 | I5: оценка доплаты ~100 тыс./камера (полная цена 200–300 тыс.) | J5: Доплата к варианту А на 3 машины
A6: 3 | B6: ИНС навигационного класса | C6: Метрологический курс ±0,1° и тангаж ±0,03° — лечит «плавающий тангаж» рига (±1–2° на подвеске) | D6: ЛМП ГКВ-6 / ГКВ-11 (Зеленоград, РФ) | E6: шт | F6: 3 | G6: 500000 | H6: =F6*G6 -> 1500000 | I6: оценка 300–800 тыс., mp-lab.ru — по запросу | J6: Ставить по итогам пилота, если программного уточнения тангажа окажется мало
A7: 4 | B7: Датчик пройденного пути (DMI) | C7: Точный линейный километраж класса дорожных лабораторий | D7: Сенсорика ИСД-3/ИСД-5 | E7: шт | F7: 3 | G7: 500000 | H7: =F7*G7 -> 1500000 | I7: оценка 300–800 тыс., sensorika.com — по запросу | J7: Старт: одометрия из CAN/OBD — бесплатно
A8: 5 | B8: Дополнительное АРМ оператора | C8: При росте потока разметки/контроля | D8: конфигурация раздела 2 | E8: компл | F8: 1 | G8: 658000 | H8: =F8*G8 -> 658000 | I8: см. раздел 2
A9: 6 | B9: NTP-сервер точного времени ГЛОНАСС/GPS | C9: Единое время сервера и бортов | D9: СТВ-01 или Raspberry Pi + GNSS PPS (10–20 тыс.) | E9: шт | F9: 1 | G9: 140000 | H9: =F9*G9 -> 140000 | I9: оценка 80–200 тыс. (tdatm.ru)
A10: 7 | B10: Аренда GPU-сервера на период пилота (3 мес) | C10: Отложить покупку сервера до подтверждения пилота | D10: 1×RTX 4090, immers.cloud | E10: мес | F10: 3 | G10: 50000 | H10: =F10*G10 -> 150000 | I10: immers.cloud
B11: ИТОГО по разделу | H11: =SUM(H4:H10) -> 5388000
